po_utils/__init__.py
po_utils/base_objects.py
po_utils/common_actions/__init__.py
po_utils/common_actions/booleans.py
po_utils/common_actions/element_interactions.py
po_utils/common_actions/gets.py
po_utils/common_actions/waits.py
page_object_utils-0.0.7.dist-info/LICENSE
page_object_utils-0.0.7.dist-info/METADATA
page_object_utils-0.0.7.dist-info/WHEEL
page_object_utils-0.0.7.dist-info/top_level.txt
page_object_utils-0.0.7.dist-info/RECORD
