Metadata-Version: 2.1
Name: page-object-utils
Version: 0.0.7
Summary: Base classes and utilities for use with browser automation
Home-page: https://github.com/matthew-bahloul/browser-utils
Author: Matthew Bahloul
Author-email: matthew.bahloul@gmail.com
License: UNKNOWN
Project-URL: Bug Tracker, https://github.com/matthew-bahloul/browser-utils/issues
Platform: UNKNOWN
Classifier: Programming Language :: Python :: 3
Classifier: License :: OSI Approved :: MIT License
Classifier: Operating System :: OS Independent
Requires-Python: >=3.6
License-File: LICENSE
Requires-Dist: selenium
